json_redactor/__init__.py
json_redactor/cli.py
json_redactor/settings.py
json_redactor/utils/__init__.py
json_redactor/utils/hash_executor.py
json_redactor/utils/helpers.py
json_redactor-0.1.1.dist-info/METADATA
json_redactor-0.1.1.dist-info/WHEEL
json_redactor-0.1.1.dist-info/entry_points.txt
json_redactor-0.1.1.dist-info/top_level.txt
json_redactor-0.1.1.dist-info/RECORD
