Metadata-Version: 2.4
Name: json-redactor
Version: 0.1.1
Summary: Add your description here
Requires-Python: >=3.12
Requires-Dist: build>=1.3.0
Requires-Dist: ijson>=3.4.0.post0
Requires-Dist: pydantic-settings>=2.12.0
Requires-Dist: twine>=6.2.0
Requires-Dist: typer>=0.20.0
